pytoshop/__init__.py
pytoshop/blending_range.py
pytoshop/codecs.py
pytoshop/color_mode.py
pytoshop/core.py
pytoshop/docs.py
pytoshop/enums.py
pytoshop/image_data.py
pytoshop/image_resources.py
pytoshop/layers.py
pytoshop/packbits.pyx
pytoshop/path.py
pytoshop/tagged_block.py
pytoshop/user/__init__.py
pytoshop/user/nested_layers.py
pytoshop/util.py
pytoshop_layer-0.1.0.dist-info/LICENSE
pytoshop_layer-0.1.0.dist-info/WHEEL
pytoshop_layer-0.1.0.dist-info/METADATA
pytoshop_layer-0.1.0.dist-info/RECORD
