Metadata-Version: 2.1
Name: pytoshop-layer
Version: 0.1.0
Summary: 
Requires-Python: >=3.10,<4.0
Classifier: Programming Language :: Python :: 3
Classifier: Programming Language :: Python :: 3.10
Classifier: Programming Language :: Python :: 3.11
Requires-Dist: Cython (>=3.0.5,<4.0.0)
Requires-Dist: numpy (>=1.26.2,<2.0.0)
